autogen_kubernetes_mcp/__init__.py
autogen_kubernetes_mcp/__main__.py
autogen_kubernetes_mcp/_executor.py
autogen_kubernetes_mcp/server.py
autogen_kubernetes_mcp-0.6.1.dist-info/METADATA
autogen_kubernetes_mcp-0.6.1.dist-info/WHEEL
autogen_kubernetes_mcp-0.6.1.dist-info/entry_points.txt
autogen_kubernetes_mcp-0.6.1.dist-info/licenses/LICENSE
autogen_kubernetes_mcp-0.6.1.dist-info/RECORD
