Metadata-Version: 2.4
Name: autogen-kubernetes-mcp
Version: 0.6.1
Summary: MPC server provides code interpreter with kubernetes workload
License-File: LICENSE
Classifier: License :: OSI Approved :: MIT License
Classifier: Operating System :: OS Independent
Classifier: Programming Language :: Python :: 3
Requires-Python: >=3.10
Requires-Dist: autogen-kubernetes>=0.5.2
Requires-Dist: mcp>=1.12.2
